laneq/__init__.py
laneq/__main__.py
laneq/gui.py
laneq/degradation_calculator/__init__.py
laneq/degradation_calculator/calculate_degradation.py
laneq/degradation_calculator/degradation_utils.py
laneq/model_suite/__init__.py
laneq/model_suite/dataloader.py
laneq/model_suite/evaluation_metrics.py
laneq/model_suite/focal_loss.py
laneq/model_suite/inference.py
laneq/model_suite/training.py
laneq/model_suite/architectures/__init__.py
laneq/model_suite/architectures/cnn.py
laneq/model_suite/architectures/cnn_sppf.py
laneq/model_suite/architectures/unet.py
laneq/model_suite/datasets/__init__.py
laneq/model_suite/datasets/classification_dataset.py
laneq/model_suite/datasets/regression_dataset.py
laneq/model_suite/datasets/segmentation_dataset.py
laneq/model_suite/utils/__init__.py
laneq/model_suite/utils/common.py
laneq/model_suite/utils/inference_utils.py
laneq/model_suite/utils/preprocessing.py
laneq-0.3.1.dist-info/licenses/LICENSE
laneq-0.3.1.dist-info/METADATA
laneq-0.3.1.dist-info/WHEEL
laneq-0.3.1.dist-info/top_level.txt
laneq-0.3.1.dist-info/RECORD
